thonnycontrib/dracula/__init__.py
thonny_dracula-0.1.2.dist-info/LICENSE
thonny_dracula-0.1.2.dist-info/METADATA
thonny_dracula-0.1.2.dist-info/WHEEL
thonny_dracula-0.1.2.dist-info/top_level.txt
thonny_dracula-0.1.2.dist-info/RECORD
