Metadata-Version: 2.1
Name: thonny-dracula
Version: 0.1.2
Summary: Dracula dark theme for Thonny IDE
Home-page: https://github.com/danspinola/thonny
Author: Daniel Spinola
Author-email: dspinola.dev@gmail.com
License: MIT
Download-URL: https://github.com/danspinola/thonny
Keywords: IDE education programming Thonny dark theme dracula
Platform: Windows
Platform: macOS
Platform: Linux
Classifier: Intended Audience :: Developers
Classifier: Intended Audience :: Education
Classifier: Intended Audience :: End Users/Desktop
Classifier: License :: OSI Approved :: MIT License
Classifier: Operating System :: MacOS
Classifier: Operating System :: Microsoft :: Windows
Classifier: Operating System :: POSIX
Classifier: Operating System :: POSIX :: Linux
Classifier: Programming Language :: Python
Classifier: Programming Language :: Python :: 3
Classifier: Topic :: Education
Classifier: Topic :: Software Development
Classifier: Topic :: Software Development :: Embedded Systems
Requires-Dist: thonny (>=3.0.0)
